toffee/__init__.py
toffee/__version.py
toffee/_base.py
toffee/_base_agent.py
toffee/_compare.py
toffee/agent.py
toffee/asynchronous.py
toffee/bundle.py
toffee/debug.py
toffee/delay.py
toffee/env.py
toffee/executor.py
toffee/funcov.py
toffee/logger.py
toffee/model.py
toffee/triggers.py
toffee/utils/__init__.py
toffee/utils/lfsr_64.py
toffee/utils/plru.py
toffee/utils/two_bits_counter.py
pytoffee-0.3.1.dist-info/METADATA
pytoffee-0.3.1.dist-info/WHEEL
pytoffee-0.3.1.dist-info/licenses/LICENSE
pytoffee-0.3.1.dist-info/RECORD
