Metadata-Version: 2.4
Name: pytoffee
Version: 0.3.1
Summary: a framework for building hardware verification platform using software method
Project-URL: Homepage, https://github.com/XS-MLVP/toffee
Project-URL: Source, https://github.com/XS-MLVP/toffee
Project-URL: Tracker, https://github.com/XS-MLVP/toffee/issues
License:                      木兰宽松许可证, 第2版
License-File: LICENSE
Classifier: Development Status :: 4 - Beta
Classifier: Intended Audience :: Developers
Classifier: License :: OSI Approved :: Mulan Permissive Software License v2 (MulanPSL-2.0)
Classifier: Topic :: Scientific/Engineering :: Electronic Design Automation (EDA)
Requires-Python: >=3.8
Provides-Extra: docs
Requires-Dist: myst-parser; extra == 'docs'
Requires-Dist: sphinx; extra == 'docs'
Requires-Dist: sphinx-autodoc-typehints; extra == 'docs'
Requires-Dist: sphinx-rtd-theme; extra == 'docs'
